apps/__init__.py
apps/api/__init__.py
apps/api/main.py
apps/collector/__init__.py
apps/collector/run.py
apps/scheduler/__init__.py
apps/scheduler/run.py
chronicle/__init__.py
chronicle/config.py
chronicle/logging.py
chronicle/utils.py
chronicle/cluster/__init__.py
chronicle/cluster/algos.py
chronicle/cluster/pipeline.py
chronicle/nlp/__init__.py
chronicle/nlp/embedding.py
chronicle/storage/__init__.py
chronicle/storage/db.py
chronicle/timeline/__init__.py
chronicle/timeline/summarize.py
chronicle_events-0.1.0.dist-info/licenses/LICENSE
chronicle_events-0.1.0.dist-info/METADATA
chronicle_events-0.1.0.dist-info/WHEEL
chronicle_events-0.1.0.dist-info/entry_points.txt
chronicle_events-0.1.0.dist-info/top_level.txt
chronicle_events-0.1.0.dist-info/RECORD
