Metadata-Version: 2.4
Name: chronicle-events
Version: 0.1.0
Summary: Intelligent event detection system using semantic embeddings, MinHash LSH deduplication, and HDBSCAN clustering
Author-email: Nick Anderson <your.email@example.com>
License: MIT
Project-URL: Homepage, https://github.com/dukeblue1994-glitch/chronicle
Project-URL: Repository, https://github.com/dukeblue1994-glitch/chronicle
Project-URL: Issues, https://github.com/dukeblue1994-glitch/chronicle/issues
Keywords: machine-learning,nlp,clustering,event-detection,news-aggregation,hdbscan,semantic-search,text-mining
Classifier: Development Status :: 4 - Beta
Classifier: Intended Audience :: Developers
Classifier: Intended Audience :: Science/Research
Classifier: License :: OSI Approved :: MIT License
Classifier: Programming Language :: Python :: 3
Classifier: Programming Language :: Python :: 3.9
Classifier: Programming Language :: Python :: 3.10
Classifier: Programming Language :: Python :: 3.11
Classifier: Programming Language :: Python :: 3.12
Classifier: Topic :: Scientific/Engineering :: Artificial Intelligence
Classifier: Topic :: Text Processing :: Linguistic
Requires-Python: >=3.9
License-File: LICENSE
Requires-Dist: fastapi<1.0.0,>=0.115.0
Requires-Dist: uvicorn<1.0.0,>=0.30.6
Requires-Dist: httpx<1.0.0,>=0.27.2
Requires-Dist: beautifulsoup4<5.0.0,>=4.12.3
Requires-Dist: readability-lxml<1.0.0,>=0.8.1
Requires-Dist: lxml<6.0.0,>=5.3.0
Requires-Dist: numpy<3.0.0,>=1.24.0
Requires-Dist: scikit-learn<2.0.0,>=1.3.0
Requires-Dist: hdbscan<1.0.0,>=0.8.38
Requires-Dist: datasketch<2.0.0,>=1.6.5
Requires-Dist: pydantic<3.0.0,>=2.9.2
Requires-Dist: pydantic-settings<3.0.0,>=2.0.0
Requires-Dist: sentence-transformers<4.0.0,>=3.0.1
Requires-Dist: python-dotenv<2.0.0,>=1.0.0
Provides-Extra: dev
Requires-Dist: pytest>=7.4.0; extra == "dev"
Requires-Dist: pytest-cov>=4.1.0; extra == "dev"
Requires-Dist: pytest-asyncio>=0.21.0; extra == "dev"
Requires-Dist: black>=23.0.0; extra == "dev"
Requires-Dist: ruff>=0.1.0; extra == "dev"
Requires-Dist: mypy>=1.7.0; extra == "dev"
Requires-Dist: types-beautifulsoup4>=4.12.0; extra == "dev"
Requires-Dist: types-requests>=2.31.0; extra == "dev"
Dynamic: license-file
